machinery/__init__.py
machinery/helpers.py
machinery/test_helpers.py
machinery/version.py
machinery/_helpers/__init__.py
machinery/_helpers/_async_mixin.py
machinery/_helpers/_context.py
machinery/_helpers/_futures.py
machinery/_helpers/_protocols.py
machinery/_helpers/_queue.py
machinery/_helpers/_queue_feeder.py
machinery/_helpers/_task_holder.py
machinery/_helpers/_ticker.py
machinery/_test_helpers/__init__.py
machinery/_test_helpers/_future_dominos.py
machinery/_test_helpers/_mocked_call_later.py
machinery_collection-0.2.dist-info/METADATA
machinery_collection-0.2.dist-info/WHEEL
machinery_collection-0.2.dist-info/licenses/LICENSE
machinery_collection-0.2.dist-info/RECORD
