Metadata-Version: 2.4
Name: machinery-collection
Version: 0.2
Summary: A collection of functionality
Project-URL: repository, https://github.com/delfick/machinery
Project-URL: changelog, https://machinery.readthedocs.io/en/latest/api/changelog.html
Project-URL: docs, https://machinery.readthedocs.io
Author-email: Stephen Moore <stephen@delfick.com>
License: MIT
License-File: LICENSE
Classifier: Intended Audience :: Developers
Classifier: License :: OSI Approved :: MIT License
Classifier: Operating System :: OS Independent
Classifier: Programming Language :: Python :: 3
Classifier: Programming Language :: Python :: 3 :: Only
Classifier: Programming Language :: Python :: 3.13
Classifier: Typing :: Typed
Requires-Python: >=3.13
